<mods ID="id-CREC-2018-02-15-pt1-PgS1170-2" version="3.3" xmlns="http://www.loc.gov/mods/v3" xmlns:exslt="http://exslt.org/common" xmlns:xlink="http://www.w3.org/1999/xlink" xmlns:xsi="http://www.w3.org/2001/XMLSchema-instance" xsi:schemaLocation="http://www.loc.gov/mods/v3 http://www.loc.gov/standards/mods/v3/mods-3-3.xsd">
<name type="corporate">
<namePart>United States Government Publishing Office</namePart>
<role>
<roleTerm authority="marcrelator" type="text">publisher</roleTerm>
<roleTerm authority="marcrelator" type="code">pbl</roleTerm>
</role>
<role>
<roleTerm authority="marcrelator" type="text">distributor</roleTerm>
<roleTerm authority="marcrelator" type="code">dst</roleTerm>
</role>
</name>
<name type="corporate">
<namePart>United States</namePart>
<namePart>Congress</namePart>
<role>
<roleTerm authority="marcrelator" type="text">author</roleTerm>
<roleTerm authority="marcrelator" type="code">aut</roleTerm>
</role>
<description>Government Organization</description>
</name>
<typeOfResource>text</typeOfResource>
<genre authority="marcgt">government publication</genre>
<language>
<languageTerm authority="iso639-2b" type="code">eng</languageTerm>
</language>
<extension>
<collectionCode>CREC</collectionCode>
<category>Proceedings of Congress and General Congressional Publications</category>
<waisDatabaseName>2018_record</waisDatabaseName>
<branch>legislative</branch>
<dateIngested>2018-02-16</dateIngested>
</extension>
<titleInfo>
<title>TEXT OF AMENDMENTS</title>
<partName>Senate</partName>
</titleInfo>
<relatedItem type="otherFormat" xlink:href="https://www.gpo.gov/fdsys/pkg/CREC-2018-02-15/html/CREC-2018-02-15-pt1-PgS1170-2.htm">
<identifier type="FDsys Unique ID">D09002ee198799550</identifier>
</relatedItem>
<relatedItem type="otherFormat" xlink:href="https://www.gpo.gov/fdsys/pkg/CREC-2018-02-15/pdf/CREC-2018-02-15-pt1-PgS1170-2.pdf">
<identifier type="FDsys Unique ID">D09002ee198799694</identifier>
</relatedItem>
<identifier type="congressional record citation">164 Cong. Rec. S1170</identifier>
<identifier type="uri">https://www.gpo.gov/fdsys/granule/CREC-2018-02-15/CREC-2018-02-15-pt1-PgS1170-2</identifier>
<identifier type="former granule identifier">cr15fe18-211</identifier>
<location>
<url access="object in context" displayLabel="Content Detail">https://www.gpo.gov/fdsys/granule/CREC-2018-02-15/CREC-2018-02-15-pt1-PgS1170-2/content-detail.html</url>
<url access="raw object" displayLabel="PDF rendition">https://www.gpo.gov/fdsys/pkg/CREC-2018-02-15/pdf/CREC-2018-02-15-pt1-PgS1170-2.pdf</url>
<url access="raw object" displayLabel="HTML rendition">https://www.gpo.gov/fdsys/pkg/CREC-2018-02-15/html/CREC-2018-02-15-pt1-PgS1170-2.htm</url>
</location>
<physicalDescription>
<extent>20 p.</extent>
</physicalDescription>
<part type="article">
<extent unit="pages">
<start>S1170</start>
<end>S1189</end>
</extent>
</part>
<name type="corporate">
<namePart>United States</namePart>
<namePart>Congress</namePart>
<namePart>Senate</namePart>
<namePart>Committee on Judiciary</namePart>
<role>
<roleTerm authority="marcrelator" type="text">associated name</roleTerm>
<roleTerm authority="marcrelator" type="code">asn</roleTerm>
</role>
<description>Government Organization</description>
</name>
<name type="corporate">
<namePart>United States</namePart>
<namePart>Congress</namePart>
<namePart>House of Representatives</namePart>
<namePart>Committee on the Judiciary</namePart>
<role>
<roleTerm authority="marcrelator" type="text">associated name</roleTerm>
<roleTerm authority="marcrelator" type="code">asn</roleTerm>
</role>
<description>Government Organization</description>
</name>
<name type="corporate">
<namePart>United States</namePart>
<namePart>Congress</namePart>
<namePart>Senate</namePart>
<namePart>Committee on Foreign Relations</namePart>
<role>
<roleTerm authority="marcrelator" type="text">associated name</roleTerm>
<roleTerm authority="marcrelator" type="code">asn</roleTerm>
</role>
<description>Government Organization</description>
</name>
<name type="corporate">
<namePart>United States</namePart>
<namePart>Congress</namePart>
<namePart>Senate</namePart>
<namePart>Committee on Appropriations</namePart>
<role>
<roleTerm authority="marcrelator" type="text">associated name</roleTerm>
<roleTerm authority="marcrelator" type="code">asn</roleTerm>
</role>
<description>Government Organization</description>
</name>
<name type="corporate">
<namePart>United States</namePart>
<namePart>Congress</namePart>
<namePart>House of Representatives</namePart>
<namePart>Committee on Foreign Affairs</namePart>
<role>
<roleTerm authority="marcrelator" type="text">associated name</roleTerm>
<roleTerm authority="marcrelator" type="code">asn</roleTerm>
</role>
<description>Government Organization</description>
</name>
<name type="corporate">
<namePart>United States</namePart>
<namePart>Congress</namePart>
<namePart>House of Representatives</namePart>
<namePart>Committee on Appropriations</namePart>
<role>
<roleTerm authority="marcrelator" type="text">associated name</roleTerm>
<roleTerm authority="marcrelator" type="code">asn</roleTerm>
</role>
<description>Government Organization</description>
</name>
<name type="corporate">
<namePart>United States</namePart>
<namePart>Congress</namePart>
<namePart>Senate</namePart>
<namePart>Committee on Homeland Security and Governmental Affairs</namePart>
<role>
<roleTerm authority="marcrelator" type="text">associated name</roleTerm>
<roleTerm authority="marcrelator" type="code">asn</roleTerm>
</role>
<description>Government Organization</description>
</name>
<name type="corporate">
<namePart>United States</namePart>
<namePart>Congress</namePart>
<namePart>House of Representatives</namePart>
<namePart>Committee on Homeland Security</namePart>
<role>
<roleTerm authority="marcrelator" type="text">associated name</roleTerm>
<roleTerm authority="marcrelator" type="code">asn</roleTerm>
</role>
<description>Government Organization</description>
</name>
<identifier type="preferred citation">164 Cong. Rec. S1170</identifier>
<extension>
<searchTitle>TEXT OF AMENDMENTS; Congressional Record Vol. 164, No. 30</searchTitle>
<granuleClass>SENATE</granuleClass>
<accessId>CREC-2018-02-15-pt1-PgS1170-2</accessId>
<subGranuleClass>SAMENDMENTTEXT</subGranuleClass>
<pagePrefix>S</pagePrefix>
<bookNumber>1</bookNumber>
<chamber>SENATE</chamber>
<granuleDate>2018-02-15</granuleDate>
<bill congress="115" context="OTHER" number="946" type="S"/>
<bill congress="115" context="FIRSTPARAGRAPH" number="2579" type="HR"/>
<bill congress="115" context="OTHER" number="2579" type="HR"/>
<congCommittee authorityId="ssju00" chamber="S" congress="115" type="S">
<name type="authority-standard">Committee on Judiciary</name>
<name type="authority-short">Judiciary</name>
</congCommittee>
<congCommittee authorityId="hsju00" chamber="H" congress="115" type="S">
<name type="authority-standard">Committee on the Judiciary</name>
<name type="authority-short">Judiciary</name>
</congCommittee>
<congCommittee authorityId="ssfr00" chamber="S" congress="115" type="S">
<name type="authority-standard">Committee on Foreign Relations</name>
<name type="authority-short">Foreign Relations</name>
</congCommittee>
<congCommittee authorityId="ssap00" chamber="S" congress="115" type="S">
<name type="authority-standard">Committee on Appropriations</name>
<name type="authority-short">Appropriations</name>
</congCommittee>
<congCommittee authorityId="hsfa00" chamber="H" congress="115" type="S">
<name type="authority-standard">Committee on Foreign Affairs</name>
<name type="authority-short">Foreign Affairs</name>
</congCommittee>
<congCommittee authorityId="hsap00" chamber="H" congress="115" type="S">
<name type="authority-standard">Committee on Appropriations</name>
<name type="authority-short">Appropriations</name>
</congCommittee>
<congCommittee authorityId="ssga00" chamber="S" congress="115" type="S">
<name type="authority-standard">Committee on Homeland Security and Governmental Affairs</name>
<name type="authority-short">Homeland and Governmental Affairs</name>
</congCommittee>
<congCommittee authorityId="hshm00" chamber="H" congress="115" type="S">
<name type="authority-standard">Committee on Homeland Security</name>
<name type="authority-short">Homeland Security</name>
</congCommittee>
<law congress="104" isPrivate="false" number="208"/>
<law congress="107" isPrivate="false" number="273"/>
<law congress="108" isPrivate="false" number="449"/>
<law congress="114" isPrivate="false" number="125"/>
<USCode title="5">
<section detail="(b)" number="552"/>
</USCode>
<USCode title="6">
<section detail="(a)" number="279"/>
<section detail="(b)(4)" number="279"/>
<section detail="(g)" number="279"/>
</USCode>
<USCode title="8">
<section number="1101"/>
<section detail="(a)(43)" number="1101"/>
<section detail="et seq." number="1101"/>
<section detail="et seq." number="1151"/>
<section number="1152"/>
<section detail="(a)(2)" number="1152"/>
<section detail="(b)" number="1152"/>
<section detail="(b)" number="1153"/>
<section detail="et seq." number="1181"/>
<section number="1182"/>
<section detail="(a)" number="1182"/>
<section detail="(a)(5)(a)" number="1182"/>
<section detail="(c)" number="1182"/>
<section number="1186b"/>
<section detail="(a)(2)" number="1227"/>
<section detail="(a)(3)(B)" number="1227"/>
<section number="1228"/>
<section number="1229a"/>
<section detail="(b)" number="1229a"/>
<section number="1254a"/>
<section number="1255"/>
<section detail="note" number="1255"/>
<section detail="(a)(1)(B)" number="1324"/>
<section detail="(g)" number="1357"/>
<section number="1362"/>
<section number="1613"/>
</USCode>
<USCode title="10">
<section detail="(a)" number="101"/>
</USCode>
<USCode title="15">
<section detail="et seq." number="2601"/>
</USCode>
<USCode title="18">
<section number="1028"/>
<section number="1365"/>
<section number="1425"/>
<section number="2250"/>
<section number="3006A"/>
<section number="758"/>
<section detail="(a)" number="921"/>
<section detail="(b)" number="983"/>
<section detail="(c)" number="983"/>
<section detail="(f)(8)" number="983"/>
<chapter number="46"/>
</USCode>
<USCode title="19">
<section detail="et seq." number="1401"/>
</USCode>
<USCode title="20">
<section detail="(a)" number="1001"/>
<section detail="et seq." number="6301"/>
<section number="7801"/>
</USCode>
<USCode title="21">
<section detail="et seq." number="1901"/>
<section number="813"/>
</USCode>
<USCode title="28">
<section number="133"/>
<section detail="(a)" number="133"/>
<section detail="note" number="133"/>
<section detail="(c)" number="524"/>
<section detail="(e)(3)" number="534"/>
</USCode>
<USCode title="31">
<section detail="(b)(1)" number="5332"/>
<section number="9705"/>
</USCode>
<USCode title="38">
<section number="101"/>
</USCode>
<USCode title="42">
<section number="12102"/>
<section number="16919"/>
<section detail="(i)(1)" number="3797aa"/>
<section number="408"/>
</USCode>
<USCode title="50">
<section detail="(4)" number="3003"/>
</USCode>
<statuteAtLarge volume="110">
<pages pages="3009-720"/>
</statuteAtLarge>
</extension>
<relatedItem type="isReferencedBy">
<titleInfo>
<title>United States Senate Bill 946  (115th Congress)</title>
</titleInfo>
<identifier type="Congressional Bill citation">S. 946</identifier>
<extension>
<congress>115</congress>
<context>OTHER</context>
</extension>
</relatedItem>
<relatedItem type="isReferencedBy">
<titleInfo>
<title>United States House Bill 2579  (115th Congress)</title>
</titleInfo>
<identifier type="Congressional Bill citation">H.R. 2579</identifier>
<extension>
<congress>115</congress>
<context>FIRSTPARAGRAPH</context>
</extension>
</relatedItem>
<relatedItem type="isReferencedBy">
<titleInfo>
<title>United States House Bill 2579  (115th Congress)</title>
</titleInfo>
<identifier type="Congressional Bill citation">H.R. 2579</identifier>
<extension>
<congress>115</congress>
<context>OTHER</context>
</extension>
</relatedItem>
<relatedItem type="isReferencedBy">
<titleInfo>
<title>United States Code</title>
<partNumber>Title 5 Section 552(b)</partNumber>
</titleInfo>
<identifier type="USC citation">5 U.S.C. 552(b)</identifier>
</relatedItem>
<relatedItem type="isReferencedBy">
<titleInfo>
<title>United States Code</title>
<partNumber>Title 6 Section 279(a)</partNumber>
<partNumber>Title 6 Section 279(b)(4)</partNumber>
<partNumber>Title 6 Section 279(g)</partNumber>
</titleInfo>
<identifier type="USC citation">6 U.S.C. 279(a)</identifier>
<identifier type="USC citation">6 U.S.C. 279(b)(4)</identifier>
<identifier type="USC citation">6 U.S.C. 279(g)</identifier>
</relatedItem>
<relatedItem type="isReferencedBy">
<titleInfo>
<title>United States Code</title>
<partNumber>Title 8 Section 1101</partNumber>
<partNumber>Title 8 Section 1101(a)(43)</partNumber>
<partNumber>Title 8 Section 1101et seq.</partNumber>
<partNumber>Title 8 Section 1151et seq.</partNumber>
<partNumber>Title 8 Section 1152</partNumber>
<partNumber>Title 8 Section 1152(a)(2)</partNumber>
<partNumber>Title 8 Section 1152(b)</partNumber>
<partNumber>Title 8 Section 1153(b)</partNumber>
<partNumber>Title 8 Section 1181et seq.</partNumber>
<partNumber>Title 8 Section 1182</partNumber>
<partNumber>Title 8 Section 1182(a)</partNumber>
<partNumber>Title 8 Section 1182(a)(5)(a)</partNumber>
<partNumber>Title 8 Section 1182(c)</partNumber>
<partNumber>Title 8 Section 1186b</partNumber>
<partNumber>Title 8 Section 1227(a)(2)</partNumber>
<partNumber>Title 8 Section 1227(a)(3)(B)</partNumber>
<partNumber>Title 8 Section 1228</partNumber>
<partNumber>Title 8 Section 1229a</partNumber>
<partNumber>Title 8 Section 1229a(b)</partNumber>
<partNumber>Title 8 Section 1254a</partNumber>
<partNumber>Title 8 Section 1255</partNumber>
<partNumber>Title 8 Section 1255note</partNumber>
<partNumber>Title 8 Section 1324(a)(1)(B)</partNumber>
<partNumber>Title 8 Section 1357(g)</partNumber>
<partNumber>Title 8 Section 1362</partNumber>
<partNumber>Title 8 Section 1613</partNumber>
</titleInfo>
<identifier type="USC citation">8 U.S.C. 1101</identifier>
<identifier type="USC citation">8 U.S.C. 1101(a)(43)</identifier>
<identifier type="USC citation">8 U.S.C. 1101et seq.</identifier>
<identifier type="USC citation">8 U.S.C. 1151et seq.</identifier>
<identifier type="USC citation">8 U.S.C. 1152</identifier>
<identifier type="USC citation">8 U.S.C. 1152(a)(2)</identifier>
<identifier type="USC citation">8 U.S.C. 1152(b)</identifier>
<identifier type="USC citation">8 U.S.C. 1153(b)</identifier>
<identifier type="USC citation">8 U.S.C. 1181et seq.</identifier>
<identifier type="USC citation">8 U.S.C. 1182</identifier>
<identifier type="USC citation">8 U.S.C. 1182(a)</identifier>
<identifier type="USC citation">8 U.S.C. 1182(a)(5)(a)</identifier>
<identifier type="USC citation">8 U.S.C. 1182(c)</identifier>
<identifier type="USC citation">8 U.S.C. 1186b</identifier>
<identifier type="USC citation">8 U.S.C. 1227(a)(2)</identifier>
<identifier type="USC citation">8 U.S.C. 1227(a)(3)(B)</identifier>
<identifier type="USC citation">8 U.S.C. 1228</identifier>
<identifier type="USC citation">8 U.S.C. 1229a</identifier>
<identifier type="USC citation">8 U.S.C. 1229a(b)</identifier>
<identifier type="USC citation">8 U.S.C. 1254a</identifier>
<identifier type="USC citation">8 U.S.C. 1255</identifier>
<identifier type="USC citation">8 U.S.C. 1255note</identifier>
<identifier type="USC citation">8 U.S.C. 1324(a)(1)(B)</identifier>
<identifier type="USC citation">8 U.S.C. 1357(g)</identifier>
<identifier type="USC citation">8 U.S.C. 1362</identifier>
<identifier type="USC citation">8 U.S.C. 1613</identifier>
</relatedItem>
<relatedItem type="isReferencedBy">
<titleInfo>
<title>United States Code</title>
<partNumber>Title 10 Section 101(a)</partNumber>
</titleInfo>
<identifier type="USC citation">10 U.S.C. 101(a)</identifier>
</relatedItem>
<relatedItem type="isReferencedBy">
<titleInfo>
<title>United States Code</title>
<partNumber>Title 15 Section 2601et seq.</partNumber>
</titleInfo>
<identifier type="USC citation">15 U.S.C. 2601et seq.</identifier>
</relatedItem>
<relatedItem type="isReferencedBy">
<titleInfo>
<title>United States Code</title>
<partNumber>Title 18 Section 1028</partNumber>
<partNumber>Title 18 Section 1365</partNumber>
<partNumber>Title 18 Section 1425</partNumber>
<partNumber>Title 18 Section 2250</partNumber>
<partNumber>Title 18 Section 3006A</partNumber>
<partNumber>Title 18 Section 758</partNumber>
<partNumber>Title 18 Section 921(a)</partNumber>
<partNumber>Title 18 Section 983(b)</partNumber>
<partNumber>Title 18 Section 983(c)</partNumber>
<partNumber>Title 18 Section 983(f)(8)</partNumber>
<partNumber>Title 18 Chapter 46</partNumber>
</titleInfo>
<identifier type="USC citation">18 U.S.C. 1028</identifier>
<identifier type="USC citation">18 U.S.C. 1365</identifier>
<identifier type="USC citation">18 U.S.C. 1425</identifier>
<identifier type="USC citation">18 U.S.C. 2250</identifier>
<identifier type="USC citation">18 U.S.C. 3006A</identifier>
<identifier type="USC citation">18 U.S.C. 758</identifier>
<identifier type="USC citation">18 U.S.C. 921(a)</identifier>
<identifier type="USC citation">18 U.S.C. 983(b)</identifier>
<identifier type="USC citation">18 U.S.C. 983(c)</identifier>
<identifier type="USC citation">18 U.S.C. 983(f)(8)</identifier>
<identifier type="USC citation">18 U.S.C. Chapter 46</identifier>
</relatedItem>
<relatedItem type="isReferencedBy">
<titleInfo>
<title>United States Code</title>
<partNumber>Title 19 Section 1401et seq.</partNumber>
</titleInfo>
<identifier type="USC citation">19 U.S.C. 1401et seq.</identifier>
</relatedItem>
<relatedItem type="isReferencedBy">
<titleInfo>
<title>United States Code</title>
<partNumber>Title 20 Section 1001(a)</partNumber>
<partNumber>Title 20 Section 6301et seq.</partNumber>
<partNumber>Title 20 Section 7801</partNumber>
</titleInfo>
<identifier type="USC citation">20 U.S.C. 1001(a)</identifier>
<identifier type="USC citation">20 U.S.C. 6301et seq.</identifier>
<identifier type="USC citation">20 U.S.C. 7801</identifier>
</relatedItem>
<relatedItem type="isReferencedBy">
<titleInfo>
<title>United States Code</title>
<partNumber>Title 21 Section 1901et seq.</partNumber>
<partNumber>Title 21 Section 813</partNumber>
</titleInfo>
<identifier type="USC citation">21 U.S.C. 1901et seq.</identifier>
<identifier type="USC citation">21 U.S.C. 813</identifier>
</relatedItem>
<relatedItem type="isReferencedBy">
<titleInfo>
<title>United States Code</title>
<partNumber>Title 28 Section 133</partNumber>
<partNumber>Title 28 Section 133(a)</partNumber>
<partNumber>Title 28 Section 133note</partNumber>
<partNumber>Title 28 Section 524(c)</partNumber>
<partNumber>Title 28 Section 534(e)(3)</partNumber>
</titleInfo>
<identifier type="USC citation">28 U.S.C. 133</identifier>
<identifier type="USC citation">28 U.S.C. 133(a)</identifier>
<identifier type="USC citation">28 U.S.C. 133note</identifier>
<identifier type="USC citation">28 U.S.C. 524(c)</identifier>
<identifier type="USC citation">28 U.S.C. 534(e)(3)</identifier>
</relatedItem>
<relatedItem type="isReferencedBy">
<titleInfo>
<title>United States Code</title>
<partNumber>Title 31 Section 5332(b)(1)</partNumber>
<partNumber>Title 31 Section 9705</partNumber>
</titleInfo>
<identifier type="USC citation">31 U.S.C. 5332(b)(1)</identifier>
<identifier type="USC citation">31 U.S.C. 9705</identifier>
</relatedItem>
<relatedItem type="isReferencedBy">
<titleInfo>
<title>United States Code</title>
<partNumber>Title 38 Section 101</partNumber>
</titleInfo>
<identifier type="USC citation">38 U.S.C. 101</identifier>
</relatedItem>
<relatedItem type="isReferencedBy">
<titleInfo>
<title>United States Code</title>
<partNumber>Title 42 Section 12102</partNumber>
<partNumber>Title 42 Section 16919</partNumber>
<partNumber>Title 42 Section 3797aa(i)(1)</partNumber>
<partNumber>Title 42 Section 408</partNumber>
</titleInfo>
<identifier type="USC citation">42 U.S.C. 12102</identifier>
<identifier type="USC citation">42 U.S.C. 16919</identifier>
<identifier type="USC citation">42 U.S.C. 3797aa(i)(1)</identifier>
<identifier type="USC citation">42 U.S.C. 408</identifier>
</relatedItem>
<relatedItem type="isReferencedBy">
<titleInfo>
<title>United States Code</title>
<partNumber>Title 50 Section 3003(4)</partNumber>
</titleInfo>
<identifier type="USC citation">50 U.S.C. 3003(4)</identifier>
</relatedItem>
<relatedItem type="isReferencedBy">
<titleInfo>
<title>United States Statutes at Large</title>
<partNumber>Volume 110 Page 3009-720</partNumber>
</titleInfo>
<identifier type="Statute citation">110 Stat. 3009-720</identifier>
</relatedItem>
<relatedItem>
<titleInfo>
<title>United States Public Law 104-208</title>
</titleInfo>
<identifier type="public law citation">Public Law 104-208</identifier>
</relatedItem>
<relatedItem>
<titleInfo>
<title>United States Public Law 107-273</title>
</titleInfo>
<identifier type="public law citation">Public Law 107-273</identifier>
</relatedItem>
<relatedItem>
<titleInfo>
<title>United States Public Law 108-449</title>
</titleInfo>
<identifier type="public law citation">Public Law 108-449</identifier>
</relatedItem>
<relatedItem>
<titleInfo>
<title>United States Public Law 114-125</title>
</titleInfo>
<identifier type="public law citation">Public Law 114-125</identifier>
</relatedItem>
<relatedItem ID="P0b002ee19879783c" type="host">
<titleInfo>
<title>Congressional Record</title>
<partNumber>Vol. 164, no. 30</partNumber>
</titleInfo>
<location>
<url access="object in context" displayLabel="Content Detail">https://www.gpo.gov/fdsys/pkg/CREC-2018-02-15/content-detail.html</url>
<url access="raw object" displayLabel="PDF rendition">https://www.gpo.gov/fdsys/pkg/CREC-2018-02-15/pdf/CREC-2018-02-15.pdf</url>
</location>
<part type="issue">
<extent unit="pages">
<start>H1181</start>
<end>H1214</end>
</extent>
<extent unit="pages">
<start>S1131</start>
<end>S1192</end>
</extent>
<extent unit="pages">
<start>E191</start>
<end>E198</end>
</extent>
<extent unit="pages">
<start>D171</start>
<end>D180</end>
</extent>
</part>
<originInfo>
<publisher>U.S. Government Publishing Office</publisher>
<dateIssued encoding="w3cdtf">2018-02-15</dateIssued>
<issuance>continuing</issuance>
<frequency authority="marcfrequency">daily</frequency>
</originInfo>
<physicalDescription>
<note type="source content type">deposited</note>
<digitalOrigin>born digital</digitalOrigin>
<extent>228 p.</extent>
</physicalDescription>
<classification authority="sudocs">X 1.1/A:</classification>
<classification authority="sudocs">X/A.</classification>
<identifier type="uri">https://www.gpo.gov/fdsys/pkg/CREC-2018-02-15</identifier>
<identifier type="local">P0b002ee19879783c</identifier>
<identifier type="stock number">752-002-00000-2</identifier>
<identifier type="ILS system id">000568013</identifier>
<identifier type="former package identifier">cr15fe18</identifier>
<recordInfo>
<recordContentSource authority="marcorg">DGPO</recordContentSource>
<recordCreationDate encoding="w3cdtf">2018-02-16</recordCreationDate>
<recordChangeDate encoding="w3cdtf">2018-02-16</recordChangeDate>
<recordIdentifier source="DGPO">CREC-2018-02-15</recordIdentifier>
<recordOrigin>machine generated</recordOrigin>
<languageOfCataloging>
<languageTerm authority="iso639-2b" type="code">eng</languageTerm>
</languageOfCataloging>
</recordInfo>
<accessCondition type="GPO scope determination">fdlp</accessCondition>
<extension>
<docClass>CREC</docClass>
<accessId>CREC-2018-02-15</accessId>
<volume>164</volume>
<issue>30</issue>
<congress>115</congress>
<session>2</session>
<bookCount>1</bookCount>
</extension>
</relatedItem>
</mods>